pypackage_example/__init__.py
pypackage_example/common.py
pypackage_example/foliumap.py
pypackage_example/pypackage_example.py
pypackage_example-0.4.0.dist-info/licenses/LICENSE
pypackage_example-0.4.0.dist-info/METADATA
pypackage_example-0.4.0.dist-info/WHEEL
pypackage_example-0.4.0.dist-info/entry_points.txt
pypackage_example-0.4.0.dist-info/top_level.txt
pypackage_example-0.4.0.dist-info/RECORD
